gym_toytext/__init__.py
gym_toytext/guessing_game.py
gym_toytext/hotter_colder.py
gym_toytext/kellycoinflip.py
gym_toytext/nchain.py
gym_toytext/roulette.py
gym_toytext-0.26.1.dist-info/METADATA
gym_toytext-0.26.1.dist-info/WHEEL
gym_toytext-0.26.1.dist-info/top_level.txt
gym_toytext-0.26.1.dist-info/RECORD
